auto_cmd/__init__.py
auto_cmd/cli.py
auto_cmd/core.py
auto_cmd/http_server.py
auto_cmd/mac.py
auto_cmd/utils.py
auto_cmd/win.py
auto_cmd/res/__init__.py
auto_cmd-0.0.2.dist-info/METADATA
auto_cmd-0.0.2.dist-info/WHEEL
auto_cmd-0.0.2.dist-info/entry_points.txt
auto_cmd-0.0.2.dist-info/top_level.txt
auto_cmd-0.0.2.dist-info/RECORD
